{
	"format_version": "1.8.0",
	"animations": {
		"animation.man_meme_boss.idle": {
			"loop": true,
			"animation_length": 16,
			"bones": {
				"Arm1": {
					"rotation": {
						"vector": ["-5+math.sin(query.anim_time*45)*5", 0, 0]
					}
				},
				"Arm2": {
					"rotation": {
						"vector": ["math.sin(query.anim_time*45)*-5", 0, 0]
					}
				},
				"Body": {
					"rotation": {
						"vector": ["10+math.sin(query.anim_time*45/2)*7", 0, 0]
					}
				},
				"Head": {
					"rotation": {
						"vector": ["7.5+math.sin(90+query.anim_time*45)*5", 0, 0]
					}
				},
				"Finger4": {
					"rotation": {
						"6.0": {
							"vector": [0, 0, 0]
						},
						"6.25": {
							"vector": [0, 0, 32.5]
						},
						"6.5": {
							"vector": [0, 0, 0]
						}
					}
				},
				"Finger5": {
					"rotation": {
						"6.0833": {
							"vector": [0, 0, 0]
						},
						"6.3333": {
							"vector": [0, 0, 32.5]
						},
						"6.5833": {
							"vector": [0, 0, 0]
						}
					}
				},
				"Finger6": {
					"rotation": {
						"6.1667": {
							"vector": [0, 0, 0]
						},
						"6.4167": {
							"vector": [0, 0, 32.5]
						},
						"6.6667": {
							"vector": [0, 0, 0]
						}
					}
				}
			}
		},
		"animation.man_meme_boss.walk": {
			"loop": true,
			"animation_length": 16,
			"bones": {
				"Arm1": {
					"rotation": {
						"vector": ["-5+math.sin(query.anim_time*45)*20", 0, 0]
					}
				},
				"Arm2": {
					"rotation": {
						"vector": ["math.sin(query.anim_time*45)*-5", 0, 0]
					}
				},
				"Leg2": {
					"rotation": {
						"vector": [0, 0, "-5+math.sin(query.anim_time*45)*30"]
					}
				},
				"LowerLeg2": {
					"rotation": {
						"vector": [0, 0, "20+math.sin(-90+query.anim_time*45)*20"]
					}
				},
				"Leg1": {
					"rotation": {
						"vector": [0, 0, "-5+math.sin(query.anim_time*45)*-30"]
					}
				},
				"LowerLeg1": {
					"rotation": {
						"vector": [0, 0, "20+math.sin(-90+query.anim_time*45)*-20"]
					}
				},
				"Body": {
					"rotation": {
						"vector": ["10+math.sin(query.anim_time*45/2)*7", 0, 0]
					}
				},
				"Head": {
					"rotation": {
						"vector": ["7.5+math.sin(90+query.anim_time*45)*5", 0, 0]
					}
				}
			}
		},
		"animation.man_meme_boss.run": {
			"loop": true,
			"animation_length": 16,
			"bones": {
				"Arm1": {
					"rotation": {
						"vector": ["-5+math.sin(query.anim_time*90)*20", 0, 0]
					}
				},
				"Arm2": {
					"rotation": {
						"vector": ["math.sin(query.anim_time*90)*-5", 0, 0]
					}
				},
				"Leg2": {
					"rotation": {
						"vector": [0, 0, "-5+math.sin(query.anim_time*90)*35"]
					}
				},
				"LowerLeg2": {
					"rotation": {
						"vector": [0, 0, "20+math.sin(-90+query.anim_time*90)*20"]
					}
				},
				"Leg1": {
					"rotation": {
						"vector": [0, 0, "-5+math.sin(query.anim_time*90)*-35"]
					}
				},
				"LowerLeg1": {
					"rotation": {
						"vector": [0, 0, "20+math.sin(-90+query.anim_time*90)*-20"]
					}
				},
				"Body": {
					"rotation": {
						"vector": ["10+math.sin(query.anim_time*45)*7", 0, 0]
					}
				},
				"Head": {
					"rotation": {
						"vector": ["7.5+math.sin(90+query.anim_time*90)*9", 0, 0]
					}
				},
				"bone": {
					"position": {
						"0.0": {
							"vector": [0, 0, 0]
						},
						"16.0": {
							"vector": [0, 0, "-500*0"]
						}
					}
				},
				"Forearm1": {
					"rotation": {
						"vector": ["-20+math.sin(-45+query.anim_time*90)*20", 0, 0]
					}
				}
			}
		},
		"animation.man_meme_boss.swing": {
			"animation_length": 3,
			"bones": {
				"Leg2": {
					"rotation": {
						"0.0": {
							"vector": [0, 0, 0]
						},
						"0.625": {
							"vector": [-12.5, 35, -20]
						},
						"1.5417": {
							"vector": [0, 0, 0]
						}
					}
				},
				"LowerLeg2": {
					"rotation": {
						"0.0": {
							"vector": [0, 0, 0]
						},
						"0.625": {
							"vector": [0, 0, 17.5]
						},
						"1.5417": {
							"vector": [0, 0, 0]
						}
					}
				},
				"Body": {
					"rotation": {
						"0.0": {
							"vector": [0, 0, 0]
						},
						"0.7917": {
							"vector": [0, 17.5, 0],
							"easing": "easeInOutSine"
						},
						"1.5833": {
							"vector": [0, -32.5, 0],
							"easing": "easeInOutQuad"
						},
						"2.5": {
							"vector": [0, 0, 0],
							"easing": "easeInOutSine"
						}
					}
				},
				"Arm1": {
					"rotation": {
						"0.0": {
							"vector": [0, 0, 0]
						},
						"0.8333": {
							"vector": [10, -15, -7.5],
							"easing": "easeInOutSine"
						},
						"1.7917": {
							"vector": [0, 0, 0],
							"easing": "easeInSine"
						}
					}
				},
				"Forearm1": {
					"rotation": {
						"0.0": {
							"vector": [0, 0, 0]
						},
						"0.8333": {
							"vector": [0, 0, 10],
							"easing": "easeInOutQuad"
						},
						"1.7917": {
							"vector": [0, 0, 0],
							"easing": "easeInOutSine"
						}
					}
				},
				"Arm2": {
					"rotation": {
						"0.0": {
							"vector": [0, 0, 0]
						},
						"0.875": {
							"vector": [-82.5, 0, -35],
							"easing": "easeInOutQuad"
						},
						"1.2917": {
							"vector": [-30, 17.5, -27.5],
							"easing": "easeInOutQuad"
						},
						"2.5417": {
							"vector": [0, 0, 0],
							"easing": "easeInOutQuart"
						}
					}
				},
				"Forearm2": {
					"rotation": {
						"0.0": {
							"vector": [0, 0, 0]
						},
						"1.2917": {
							"vector": [120, 0, -7.5],
							"easing": "easeInSine"
						},
						"3.0": {
							"vector": [0, 0, 0],
							"easing": "easeInOutQuart"
						}
					}
				}
			}
		},
		"animation.man_meme_boss.smash": {
			"animation_length": 6.5,
			"bones": {
				"Leg2": {
					"rotation": {
						"0.0": {
							"vector": [0, 0, 0]
						},
						"2.375": {
							"vector": [0, 0, -42.5],
							"easing": "easeInOutSine"
						},
						"4.0": {
							"vector": [0, 0, -65],
							"easing": "easeInExpo"
						},
						"4.625": {
							"vector": [0, 0, -65],
							"easing": "easeInExpo"
						},
						"5.5": {
							"vector": [0, 0, -5],
							"easing": "easeInBack",
							"easingArgs": [1]
						},
						"5.875": {
							"vector": [0, 0, 0],
							"easing": "easeOutQuint"
						}
					}
				},
				"LowerLeg2": {
					"rotation": {
						"0.0": {
							"vector": [0, 0, 0]
						},
						"2.375": {
							"vector": [0, 0, 35],
							"easing": "easeInOutQuad"
						},
						"4.0": {
							"vector": [0, 0, 65],
							"easing": "easeInExpo"
						},
						"4.625": {
							"vector": [0, 0, 65],
							"easing": "easeInExpo"
						},
						"5.5": {
							"vector": [0, 0, 8],
							"easing": "easeInBack",
							"easingArgs": [-1]
						},
						"5.875": {
							"vector": [0, 0, 0],
							"easing": "easeOutQuart"
						}
					}
				},
				"Body": {
					"rotation": {
						"0.0": {
							"vector": [0, 0, 0]
						},
						"2.5833": {
							"vector": [-27.5, 0, 0],
							"easing": "easeInOutBack"
						},
						"4.0833": {
							"vector": [42.5, 5, 0],
							"easing": "easeInExpo"
						},
						"4.5": {
							"vector": [42.5, 5, 0],
							"easing": "easeOutExpo"
						},
						"6.0": {
							"vector": [0, 0, 0],
							"easing": "easeInOutQuad"
						}
					}
				},
				"Arm1": {
					"rotation": {
						"0.0": {
							"vector": [0, 0, 0]
						},
						"2.25": {
							"vector": [-162.5, 0, -15],
							"easing": "easeInOutSine"
						},
						"4.0": {
							"vector": [-35, 15, -2.5],
							"easing": "easeInExpo"
						},
						"4.5": {
							"vector": [-35, 15, -2.5],
							"easing": "easeInExpo"
						},
						"6.0": {
							"vector": [0, 0, 0],
							"easing": "easeInOutSine"
						}
					}
				},
				"Forearm1": {
					"rotation": {
						"0.0": {
							"vector": [0, 0, 0]
						},
						"0.8333": {
							"vector": [-50, 0, 10],
							"easing": "easeInOutQuad"
						},
						"2.5": {
							"vector": [-75, 27.5, 0],
							"easing": "easeInOutSine"
						},
						"4.0": {
							"vector": [-57.5, 10, 10],
							"easing": "easeInExpo"
						},
						"4.5": {
							"vector": [-57.5, 10, 10],
							"easing": "easeInExpo"
						},
						"6.0": {
							"vector": [0, 0, 0],
							"easing": "easeInOutSine"
						}
					}
				},
				"Arm2": {
					"rotation": {
						"0.0": {
							"vector": [0, 0, 0]
						},
						"2.0": {
							"vector": [-162.5, 0, 15],
							"easing": "easeInOutQuad"
						},
						"4.0": {
							"vector": [-30.5, -22, 17.5],
							"easing": "easeInExpo"
						},
						"4.5": {
							"vector": [-30.5, -22, 17.5],
							"easing": "easeInExpo"
						},
						"6.0": {
							"vector": [0, 0, 0],
							"easing": "easeInOutSine"
						}
					}
				},
				"Forearm2": {
					"rotation": {
						"0.0": {
							"vector": [0, 0, 0]
						},
						"2.25": {
							"vector": [55, 0, 0],
							"easing": "easeInOutQuad"
						},
						"4.0": {
							"vector": [65, -2.5, -7.5],
							"easing": "easeInExpo"
						},
						"4.5": {
							"vector": [65, -2.5, -7.5],
							"easing": "easeInExpo"
						},
						"6.25": {
							"vector": [0, 0, 0],
							"easing": "easeInOutQuad"
						}
					}
				},
				"bone": {
					"position": {
						"2.375": {
							"vector": [0, 0, 0]
						},
						"3.0": {
							"vector": [0, 0, 0]
						},
						"4.0": {
							"vector": [0, -17, -17],
							"easing": "easeInExpo"
						},
						"5.5": {
							"vector": [0, 0, 0],
							"easing": "easeInQuart"
						}
					}
				},
				"Finger1": {
					"rotation": {
						"0.0": {
							"vector": [0, 0, 0]
						},
						"2.5": {
							"vector": [0, 0, -62.5]
						},
						"6.0": {
							"vector": [0, 0, 0],
							"easing": "easeInOutSine"
						}
					}
				},
				"Finger2": {
					"rotation": {
						"0.0": {
							"vector": [0, 0, 0]
						},
						"2.5": {
							"vector": [0, 0, -57.5]
						},
						"6.0": {
							"vector": [0, 0, 0],
							"easing": "easeInOutSine"
						}
					}
				},
				"Finger3": {
					"rotation": {
						"0.0": {
							"vector": [0, 0, 0]
						},
						"2.5": {
							"vector": [0, 0, -47.5]
						},
						"6.0": {
							"vector": [0, 0, 0],
							"easing": "easeInOutSine"
						}
					}
				},
				"Thumb1": {
					"rotation": {
						"0.0": {
							"vector": [0, 0, 0]
						},
						"2.5": {
							"vector": [-40, 62.5, 2.5]
						},
						"6.0": {
							"vector": [0, 0, 0],
							"easing": "easeInOutSine"
						}
					}
				},
				"Head": {
					"rotation": {
						"0.0": {
							"vector": [0, 0, 0]
						},
						"4.0": {
							"vector": [27.5, 0, 0],
							"easing": "easeInExpo"
						},
						"4.25": {
							"vector": [27.5, 0, 0],
							"easing": "easeInExpo"
						},
						"5.5": {
							"vector": [-15, 0, 0],
							"easing": "easeInOutSine"
						},
						"6.5": {
							"vector": [0, 0, 0],
							"easing": "easeInOutSine"
						}
					}
				},
				"LowerLeg1": {
					"rotation": {
						"0.0": {
							"vector": [0, 0, 0]
						},
						"3.0": {
							"vector": [0, 0, 0]
						},
						"4.0": {
							"vector": [0, 0, 90],
							"easing": "easeInExpo"
						},
						"5.5": {
							"vector": [0, 0, 9],
							"easing": "easeInQuart"
						},
						"5.875": {
							"vector": [0, 0, 0],
							"easing": "easeOutQuint"
						}
					}
				}
			}
		},
		"animation.man_meme_boss.swing_aim": {
			"animation_length": 3,
			"bones": {
				"Arm1": {
					"rotation": {
						"0.0": {
							"vector": [0, 0, 0]
						},
						"1.0": {
							"vector": [-90, 15, -87.5],
							"easing": "easeInOutQuad"
						},
						"2.75": {
							"vector": [0, 0, 0],
							"easing": "easeOutQuad"
						}
					}
				},
				"Finger1": {
					"rotation": {
						"0.0": {
							"vector": [0, 0, 0]
						},
						"1.0": {
							"vector": [0, 0, -162.5],
							"easing": "easeInOutQuad"
						},
						"2.75": {
							"vector": [0, 0, 0],
							"easing": "easeOutQuad"
						}
					}
				},
				"Finger2": {
					"rotation": {
						"0.0": {
							"vector": [0, 0, 0]
						},
						"1.0": {
							"vector": [0, 0, -142.5],
							"easing": "easeInOutQuad"
						},
						"2.75": {
							"vector": [0, 0, 0],
							"easing": "easeOutQuad"
						}
					}
				},
				"Finger3": {
					"rotation": {
						"0.0": {
							"vector": [0, 0, 0]
						},
						"1.0": {
							"vector": [0, 0, -145],
							"easing": "easeInOutQuad"
						},
						"2.75": {
							"vector": [0, 0, 0],
							"easing": "easeOutQuad"
						}
					}
				},
				"Thumb1": {
					"rotation": {
						"0.0": {
							"vector": [0, 0, 0]
						},
						"1.0": {
							"vector": [-155, 0, 0],
							"easing": "easeInOutQuad"
						},
						"2.75": {
							"vector": [0, 0, 0],
							"easing": "easeOutQuad"
						}
					}
				}
			}
		},
		"animation.man_meme_boss.death": {
			"animation_length": 5,
			"bones": {
				"bone": {
					"rotation": {
						"vector": [0, 0, 0]
					},
					"position": {
						"0.0": {
							"vector": [0, 0, 0]
						},
						"1.0": {
							"vector": [0, -10, 0]
						}
					}
				},
				"Body": {
					"rotation": {
						"0.0": {
							"vector": [0, 0, 0]
						},
						"1.0": {
							"vector": [47.5, 0, 0],
							"easing": "easeInCubic"
						},
						"1.4167": {
							"vector": [52.5, 0, 0],
							"easing": "easeOutQuart"
						}
					}
				},
				"Arm1": {
					"rotation": {
						"0.0": {
							"vector": [0, 0, 0]
						},
						"1.0": {
							"vector": [0, 0, 0]
						}
					}
				},
				"Forearm1": {
					"rotation": {
						"0.0": {
							"vector": [0, 0, 0]
						},
						"1.0": {
							"vector": [-55, 0, 0]
						}
					}
				},
				"Arm2": {
					"rotation": {
						"0.0": {
							"vector": [0, 0, 0]
						},
						"1.0": {
							"vector": [-62.5, 0, 0],
							"easing": "easeInOutSine"
						}
					}
				},
				"Forearm2": {
					"rotation": {
						"0.0": {
							"vector": [0, 0, 0]
						},
						"1.0": {
							"vector": [47.5, 0, -7.5],
							"easing": "easeInQuart"
						}
					}
				},
				"Head": {
					"rotation": {
						"0.0": {
							"vector": [0, 0, 0]
						},
						"0.875": {
							"vector": [25, 0, 0],
							"easing": "easeOutCubic"
						},
						"2.75": {
							"vector": [47.5, 0, 0],
							"easing": "easeInBounce",
							"easingArgs": [0.5]
						}
					}
				},
				"Leg1": {
					"rotation": {
						"0.0": {
							"vector": [0, 0, 0]
						},
						"1.0": {
							"vector": [0, 0, -52.5]
						}
					}
				},
				"LowerLeg1": {
					"rotation": {
						"0.0": {
							"vector": [0, 0, 0]
						},
						"1.0": {
							"vector": [0, 0, 55]
						}
					}
				},
				"Leg2": {
					"rotation": {
						"0.0": {
							"vector": [0, 0, 0]
						},
						"1.0": {
							"vector": [0, 0, 30]
						}
					}
				},
				"LowerLeg2": {
					"rotation": {
						"0.0": {
							"vector": [0, 0, 0]
						},
						"1.0": {
							"vector": [0, 0, 30]
						}
					}
				}
			}
		}
	},
	"geckolib_format_version": 2
}